marius/__init__.py
marius/core/__init__.py
marius/core/task.py
marius/core/timeline.py
marius/core/utils.py
marius/core/wait.py
marius/helper/__init__.py
marius/helper/every.py
marius-0.1.3.dist-info/METADATA
marius-0.1.3.dist-info/RECORD
marius-0.1.3.dist-info/WHEEL
marius-0.1.3.dist-info/top_level.txt
