Metadata-Version: 2.1
Name: marius
Version: 0.1.3
Summary: Light weight job scheduling tool with more performance and scalability.
Home-page: https://github.com/Jack-Kingdom/marius.git
Author: Jack King
Author-email: email@qiaohong.org
License: MIT
Platform: UNKNOWN
Classifier: Intended Audience :: Developers
Classifier: License :: OSI Approved :: MIT License
Classifier: Programming Language :: Python
Classifier: Programming Language :: Python :: 3
Classifier: Programming Language :: Python :: 2.7
Classifier: Programming Language :: Python :: 3.5
Classifier: Programming Language :: Python :: 3.6
Classifier: Natural Language :: English
